win_auto_tiny/__init__.py
win_auto_tiny/dpi_utils.py
win_auto_tiny/keyboard.py
win_auto_tiny/mouse.py
win_auto_tiny/process.py
win_auto_tiny/win32_draw.py
win_auto_tiny/window_utils.py
win_auto_tiny-0.1.2.dist-info/LICENSE
win_auto_tiny-0.1.2.dist-info/METADATA
win_auto_tiny-0.1.2.dist-info/WHEEL
win_auto_tiny-0.1.2.dist-info/RECORD
