Metadata-Version: 2.1
Name: win_auto_tiny
Version: 0.1.2
Summary: A lightweight Python library for automating Windows GUI tasks, featuring simple functions to run applications, find windows, click, and type text.
Home-page: https://github.com/th-yoo/win_auto_tiny
License: MIT
Keywords: win32,automation,lightweight,GUI,windows,mouse,keyboard,DPI
Author: th yoo
Author-email: taihyungyoo@gmail.com
Requires-Python: >=3.9,<4.0
Classifier: License :: OSI Approved :: MIT License
Classifier: Programming Language :: Python :: 3
Classifier: Programming Language :: Python :: 3.9
Classifier: Programming Language :: Python :: 3.10
Classifier: Programming Language :: Python :: 3.11
Classifier: Programming Language :: Python :: 3.12
Requires-Dist: pywin32 (>=300) ; sys_platform == "win32"
